pynpmd/__init__.py
pynpmd/access_dict.py
pynpmd/dep_cache.py
pynpmd/npm_helper.py
pynpm_download-0.2.dist-info/LICENSE
pynpm_download-0.2.dist-info/METADATA
pynpm_download-0.2.dist-info/WHEEL
pynpm_download-0.2.dist-info/top_level.txt
pynpm_download-0.2.dist-info/RECORD
