Metadata-Version: 2.1
Name: pynpm-download
Version: 0.2
Summary: A Js Dependency Downloader using NPM Public Registry API
Home-page: https://gitlab.com/mmonschau/pynpm-download
Author: Michael Monschau
Author-email: dev@michael-monschau.de
License: MIT
Keywords: javascript,dependency management,web development
Platform: UNKNOWN
Classifier: Programming Language :: Python :: 3
Classifier: Programming Language :: Python :: 3.6
Classifier: Operating System :: OS Independent
Classifier: License :: OSI Approved :: MIT License
Classifier: Development Status :: 5 - Production/Stable
Classifier: Intended Audience :: Developers
Requires-Python: >=3.6
License-File: LICENSE
